src/__init__.py
src/simulation.py
src/visualization.py
tests/__init__.py
tests/test_simulation.py
tests/test_visualization.py
epidemiological_model-1.0.3.dist-info/LICENSE
epidemiological_model-1.0.3.dist-info/METADATA
epidemiological_model-1.0.3.dist-info/WHEEL
epidemiological_model-1.0.3.dist-info/entry_points.txt
epidemiological_model-1.0.3.dist-info/top_level.txt
epidemiological_model-1.0.3.dist-info/RECORD
