Metadata-Version: 2.1
Name: epidemiological-model
Version: 1.0.3
Summary: A Python package for epidemiological modelling
Home-page: https://github.com/babak2/epidemiological_model
Author: Babak Mahdavi Ardestani
Author-email: babak.m.ardestani@gmail.com
License: UNKNOWN
Platform: UNKNOWN
Classifier: Programming Language :: Python :: 3
Classifier: License :: OSI Approved :: MIT License
Classifier: Operating System :: OS Independent
Requires-Dist: matplotlib (==3.5.1)
Requires-Dist: numpy (==1.24.4)
